py_research-5.1.3.dist-info/METADATA
py_research-5.1.3.dist-info/WHEEL
py_research-5.1.3.dist-info/entry_points.txt
py_research-5.1.3.dist-info/licenses/LICENSE
py_research/__init__.py
py_research/caching.py
py_research/colors.py
py_research/data.py
py_research/db/__init__.py
py_research/db/base.py
py_research/db/conflicts.py
py_research/db/importing.py
py_research/enums.py
py_research/files.py
py_research/geo.py
py_research/hashing.py
py_research/intl.py
py_research/plots/__init__.py
py_research/plots/responsive_plotly.js
py_research/ranking.py
py_research/reflect/__init__.py
py_research/reflect/deps.py
py_research/reflect/dist.py
py_research/reflect/env.py
py_research/reflect/ref.py
py_research/reflect/runtime.py
py_research/sql.py
py_research/stats.py
py_research/tables.py
py_research/telemetry.py
py_research/time.py
py_research-5.1.3.dist-info/RECORD
