Metadata-Version: 2.1
Name: py-research
Version: 5.1.3
Summary: Collection of utilities for R&D coding in Python 🐍
Author-Email: Lorenzo Wormer <l.wormer@mailbox.org>
Project-URL: Documentation, https://cloudlane-one.github.io/py-research/
Requires-Python: <3.14,>=3.11
Requires-Dist: pandas<3.0,>=2.2.0
Requires-Dist: PyYAML<7.0,>=6.0
Requires-Dist: openpyxl<4.0.0,>=3.0.9
Requires-Dist: country-converter<2.0,>=1.2
Requires-Dist: pydantic<3.0,>=2.5.3
Requires-Dist: streamlit<2.0.0,>=1.7.0
Requires-Dist: tqdm<5.0.0,>=4.62.3
Requires-Dist: sqlalchemy<3.0.0,>=2.0.7
Requires-Dist: strenum<1.0.0,>=0.4.10
Requires-Dist: stqdm<1.0.0,>=0.0.5
Requires-Dist: structlog<26.0.0,>=25
Requires-Dist: webcolors>=1.13
Requires-Dist: deep-translator<2.0.0,>=1.11.0
Requires-Dist: babel<3.0.0,>=2.12.1
Requires-Dist: numpy>=2.0.0
Requires-Dist: pdfkit<2.0.0,>=1.0.0
Requires-Dist: imgkit<2.0.0,>=1.2.3
Requires-Dist: typing-extensions<5.0.0,>=4.7.1
Requires-Dist: plotly<7.0.0,>=5.16.1
Requires-Dist: GitPython>=3.1.40
Requires-Dist: beautifulsoup4>=4.12.2
Requires-Dist: importlib-metadata>=6.11.0
Requires-Dist: pandas-stubs>=2.1.4.231227
Requires-Dist: packaging>=23.2
Requires-Dist: requests>=2.31.0
Requires-Dist: pydantic-core>=2.14.6
Requires-Dist: notebook>=7.0.6
Requires-Dist: ipywidgets>=8.1.1
Requires-Dist: ipython>=8.21.0
Requires-Dist: sphinx>=7.2.6
